CHANGELOG.md
CONTRIBUTING.md
LICENSE
keycloak/__init__.py
keycloak/_version.py
keycloak/authorization/__init__.py
keycloak/authorization/permission.py
keycloak/authorization/policy.py
keycloak/authorization/role.py
keycloak/connection.py
keycloak/exceptions.py
keycloak/keycloak_admin.py
keycloak/keycloak_openid.py
keycloak/keycloak_uma.py
keycloak/openid_connection.py
keycloak/uma_permissions.py
keycloak/urls_patterns.py
python_keycloak_async-2.17.1.dist-info/LICENSE
python_keycloak_async-2.17.1.dist-info/METADATA
python_keycloak_async-2.17.1.dist-info/WHEEL
python_keycloak_async-2.17.1.dist-info/RECORD
