Metadata-Version: 2.1
Name: python-keycloak-async
Version: 2.17.1
Summary: python-keycloak-async is a Python package providing access to the Keycloak API.
License: MIT
Keywords: keycloak,asyncio,openid,oidc
Author: Quang Phan
Author-email: quangpq.uit@gmail.com
Requires-Python: >=3.9,<4.0
Classifier: Development Status :: 3 - Alpha
Classifier: License :: OSI Approved :: MIT License
Classifier: Operating System :: MacOS
Classifier: Operating System :: Microsoft :: Windows
Classifier: Operating System :: Unix
Classifier: Programming Language :: Python :: 3
Classifier: Programming Language :: Python :: 3.9
Classifier: Programming Language :: Python :: 3.10
Classifier: Programming Language :: Python :: 3.11
Classifier: Programming Language :: Python :: 3
Classifier: Topic :: Utilities
Provides-Extra: docs
Requires-Dist: Sphinx (>=5.3.0,<6.0.0) ; extra == "docs"
Requires-Dist: aiofiles (>=23.1.0,<24.0.0)
Requires-Dist: alabaster (>=0.7.12,<0.8.0) ; extra == "docs"
Requires-Dist: commonmark (>=0.9.1,<0.10.0) ; extra == "docs"
Requires-Dist: deprecation (>=2.1.0,<3.0.0)
Requires-Dist: httpx (>=0.24.0,<0.25.0)
Requires-Dist: m2r2 (>=0.3.2,<0.4.0) ; extra == "docs"
Requires-Dist: mock (>=4.0.3,<5.0.0) ; extra == "docs"
Requires-Dist: python-jose (>=3.3.0,<4.0.0)
Requires-Dist: readthedocs-sphinx-ext (>=2.1.9,<3.0.0) ; extra == "docs"
Requires-Dist: recommonmark (>=0.7.1,<0.8.0) ; extra == "docs"
Requires-Dist: requests-toolbelt (>=1.0.0,<2.0.0)
Requires-Dist: sphinx-autoapi (>=2.0.0,<3.0.0) ; extra == "docs"
Requires-Dist: sphinx-rtd-theme (>=1.0.0,<2.0.0) ; extra == "docs"
Project-URL: Documentation, https://github.com/quangpq/python-keycloak-async
Project-URL: Issue tracker, https://github.com/quangpq/python-keycloak-async/issues
